tensortrade/__init__.py
tensortrade/version.py
tensortrade/agents/__init__.py
tensortrade/agents/a2c_agent.py
tensortrade/agents/agent.py
tensortrade/agents/dqn_agent.py
tensortrade/agents/replay_memory.py
tensortrade/agents/parallel/__init__.py
tensortrade/agents/parallel/parallel_dqn_agent.py
tensortrade/agents/parallel/parallel_dqn_model.py
tensortrade/agents/parallel/parallel_dqn_optimizer.py
tensortrade/agents/parallel/parallel_dqn_trainer.py
tensortrade/agents/parallel/parallel_queue.py
tensortrade/contrib/__init__.py
tensortrade/core/__init__.py
tensortrade/core/base.py
tensortrade/core/clock.py
tensortrade/core/component.py
tensortrade/core/context.py
tensortrade/core/exceptions.py
tensortrade/core/registry.py
tensortrade/data/__init__.py
tensortrade/data/cdd.py
tensortrade/env/__init__.py
tensortrade/env/default/__init__.py
tensortrade/env/default/actions.py
tensortrade/env/default/informers.py
tensortrade/env/default/observers.py
tensortrade/env/default/renderers.py
tensortrade/env/default/rewards.py
tensortrade/env/default/stoppers.py
tensortrade/env/generic/__init__.py
tensortrade/env/generic/environment.py
tensortrade/env/generic/components/__init__.py
tensortrade/env/generic/components/action_scheme.py
tensortrade/env/generic/components/informer.py
tensortrade/env/generic/components/observer.py
tensortrade/env/generic/components/renderer.py
tensortrade/env/generic/components/reward_scheme.py
tensortrade/env/generic/components/stopper.py
tensortrade/feed/__init__.py
tensortrade/feed/api/__init__.py
tensortrade/feed/api/boolean/__init__.py
tensortrade/feed/api/boolean/operations.py
tensortrade/feed/api/float/__init__.py
tensortrade/feed/api/float/accumulators.py
tensortrade/feed/api/float/imputation.py
tensortrade/feed/api/float/operations.py
tensortrade/feed/api/float/ordering.py
tensortrade/feed/api/float/utils.py
tensortrade/feed/api/float/window/__init__.py
tensortrade/feed/api/float/window/ewm.py
tensortrade/feed/api/float/window/expanding.py
tensortrade-1.0.1b0.dist-info/LICENSE
tensortrade-1.0.1b0.dist-info/METADATA
tensortrade-1.0.1b0.dist-info/WHEEL
tensortrade-1.0.1b0.dist-info/top_level.txt
tensortrade-1.0.1b0.dist-info/RECORD
